{
	"author": "David W Skinner",
	"format_version": 2,
	"height": 12,
	"id": "official-w2-111",
	"metadata": {
		"import_source": "E:/godot_learning/projects/sokoban/docs/microban_levels/DavidWSkinner Microban.sok",
		"index": 111,
		"source_index": 111,
		"source_title": "Microban 111",
		"verified_by_solver": false,
		"world": 2,
		"theme": {
			"wall": "stone",
			"floor": "dirt"
		}
	},
	"name": "Microban 111",
	"tiles": [
		"######   ",
		"#    ####",
		"#    ...#",
		"#    ...#",
		"######  #",
		"  #  #  #",
		"  # $$ ##",
		"  # @$  #",
		"  # $$  #",
		"  ## $# #",
		"   #    #",
		"   ######"
	],
	"width": 9
}
